tsst_sino_backtest/__init__.py
tsst_sino_backtest/utils.py
tsst_sino_backtest/constant.py
tsst_sino_backtest/main.cpython-310-darwin.so
tsst_sino_backtest/static/holidays_search_from_2017.csv
tsst_sino_backtest/static/taipei_typhoon_holiday_from_2017.csv
tsst_sino_backtest/static/taiwan_routine_holidays_from_2017.csv
tsst_sino_backtest/static/templates/profit_report.html
tsst_sino_backtest/modules/__init__.py
tsst_sino_backtest/modules/matcher/matcher.cpython-310-darwin.so
tsst_sino_backtest/modules/matcher/__init__.py
tsst_sino_backtest/modules/ticker/ticker.cpython-310-darwin.so
tsst_sino_backtest/modules/ticker/__init__.py
tsst_sino_backtest/modules/positions/__init__.py
tsst_sino_backtest/modules/positions/positions.cpython-310-darwin.so
tsst_sino_backtest_v2-0.2.4.dist-info/RECORD
tsst_sino_backtest_v2-0.2.4.dist-info/WHEEL
tsst_sino_backtest_v2-0.2.4.dist-info/top_level.txt
tsst_sino_backtest_v2-0.2.4.dist-info/METADATA
tsst_sino_backtest_v2-0.2.4.dist-info/licenses/LICENSE
