Metadata-Version: 2.4
Name: tsst-sino-backtest-v2
Version: 0.2.4
Summary: Add your description here
Author-email: Aiaristosit <aiaristosit@gmail.com>
License: Software License Agreement (Proprietary License)
Project-URL: Homepage, https://tsst.docs.aiaristos.com/
Classifier: Programming Language :: Python :: 3
Classifier: Operating System :: Microsoft :: Windows :: Windows 10
Requires-Python: >=3.9
License-File: LICENSE
Requires-Dist: build>=1.2.2.post1
Requires-Dist: cython>=3.1.1
Requires-Dist: ipython>=8.18.1
Requires-Dist: jinja2>=3.1.6
Requires-Dist: nanoid>=2.0.0
Requires-Dist: polars>=1.29.0
Requires-Dist: pyarrow>=20.0.0
Requires-Dist: python-dotenv>=1.1.0
Requires-Dist: quantstats-lumi>=0.1.12
Requires-Dist: requests>=2.32.3
Requires-Dist: rich>=14.0.0
Requires-Dist: setuptools>=80.9.0
Requires-Dist: shioaji[speed]>=1.2.5
Requires-Dist: pyproject_hooks; sys_platform == "darwin" or sys_platform == "linux"
Requires-Dist: tomli; sys_platform == "darwin" or sys_platform == "linux"
Requires-Dist: packaging; sys_platform == "darwin" or sys_platform == "linux"
Requires-Dist: cryptography>=45.0.4
Dynamic: license-file
